kosmatau3d/__init__.py
kosmatau3d/comparison/__init__.py
kosmatau3d/comparison/model_selection.py
kosmatau3d/comparison/observation.py
kosmatau3d/grid/AlAV.dat
kosmatau3d/grid/Eimag.dat
kosmatau3d/grid/Ereal.dat
kosmatau3d/grid/RhoMassAFUV.dat
kosmatau3d/grid/Tb_linecentre.dat
kosmatau3d/grid/clumpDustTau_reduced.dat
kosmatau3d/grid/clumpDustTau_reduced2.dat
kosmatau3d/grid/clumpDustTmb_reduced.dat
kosmatau3d/grid/clumpDustTmb_reduced2.dat
kosmatau3d/grid/clumpMeanCols.dat
kosmatau3d/grid/clumpTauLineCenter_CR-11.dat
kosmatau3d/grid/clumpTauLineCenter_CR-12.dat
kosmatau3d/grid/clumpTauLineCenter_CR-13.dat
kosmatau3d/grid/clumpTauLineCenter_CR-14.dat
kosmatau3d/grid/clumpTauLineCenter_CR-15.dat
kosmatau3d/grid/clumpTauLineCenter_reduced.dat
kosmatau3d/grid/clumpTauLineCenter_reduced2.dat
kosmatau3d/grid/clumpTemperatures.dat
kosmatau3d/grid/clumpTemperatures_filled.dat
kosmatau3d/grid/clumpTmbLineCenter_CR-11.dat
kosmatau3d/grid/clumpTmbLineCenter_CR-12.dat
kosmatau3d/grid/clumpTmbLineCenter_CR-13.dat
kosmatau3d/grid/clumpTmbLineCenter_CR-14.dat
kosmatau3d/grid/clumpTmbLineCenter_CR-15.dat
kosmatau3d/grid/clumpTmbLineCenter_reduced.dat
kosmatau3d/grid/clumpTmbLineCenter_reduced2.dat
kosmatau3d/grid/clump_Tmb_LineCenter.dat
kosmatau3d/grid/clump_tau_LineCenter.dat
kosmatau3d/grid/column-densities.dat
kosmatau3d/grid/column-densities_filled.dat
kosmatau3d/grid/dustSED.dat
kosmatau3d/grid/dustmeanTauV.dat
kosmatau3d/grid/frequencies.dat
kosmatau3d/grid/frequencies2.dat
kosmatau3d/grid/interclumpDustSED.dat
kosmatau3d/grid/interclumpDustTau.dat
kosmatau3d/grid/interclumpMeanCols.dat
kosmatau3d/grid/interclumpTauFUV.dat
kosmatau3d/grid/interclumpTauLineCenter.dat
kosmatau3d/grid/interclumpTauLineCenter_reduced.dat
kosmatau3d/grid/interclumpTemperatures.dat
kosmatau3d/grid/interclumpTemperatures_filled.dat
kosmatau3d/grid/interclumpTmbLineCenter.dat
kosmatau3d/grid/interclumpTmbLineCenter_reduced.dat
kosmatau3d/grid/tau_linecentre.dat
kosmatau3d-1.0.10.dist-info/LICENSE
kosmatau3d-1.0.10.dist-info/METADATA
kosmatau3d-1.0.10.dist-info/WHEEL
kosmatau3d-1.0.10.dist-info/top_level.txt
kosmatau3d-1.0.10.dist-info/RECORD
