Metadata-Version: 2.1
Name: kosmatau3d
Version: 1.0.10
Summary: A clumpy PDR model
Home-page: https://github.com/CraigYanitski/kosmatau3d
Author: C.N. Yanitski
Author-email: Craig Yanitski <yanitski@ph1.uni-koeln.de>
Project-URL: Homepage, https://github.com/CraigYanitski/kosmatau3d
Project-URL: Bugs Tracker, https://github.com/CraigYanitski/kosmatau3d/issues
Classifier: Programming Language :: Python :: 3
Classifier: License :: OSI Approved :: GNU General Public License v3 (GPLv3)
Classifier: Operating System :: Unix
Requires-Python: >=3.6
License-File: LICENSE
Requires-Dist: astrokit
Requires-Dist: astropy
Requires-Dist: cygrid
Requires-Dist: dill
Requires-Dist: jupyter-book
Requires-Dist: jupyterlab
Requires-Dist: matplotlib
Requires-Dist: numba >=0.49.1
Requires-Dist: numpy
Requires-Dist: pandas
Requires-Dist: pyqt5
Requires-Dist: scikit-learn
Requires-Dist: scipy
Requires-Dist: spectres
Requires-Dist: sphinx
Requires-Dist: sphinx-autoapi
Requires-Dist: sympy
Requires-Dist: tqdm
